Workbook

Sheet Start Here
A1: POULTRY PRODUCTION COST OPTIMIZATION & FINANCIAL FEASIBILITY
A2: Purpose | B2: Portfolio financial model built from the actual 50-bird cycle plus explicitly labelled scenario illustrations.
A3: Critical warning | B3: Preliminary surplus is NOT confirmed net profit; unknown expenses and capital expenditure are not included.
A4: Scenario warning | B4: The 1,000/3,000/5,000 calculations are linear baseline-equivalent illustrations, not forecasts.
A5: How to use | B5: Edit yellow cells in Model Inputs. Fill unknown cost assumptions before using results for decisions.
A6: Historical source | B6: Actual farm operation around Nov-Dec 2025, Anambra State, Nigeria; values supplied by user and source research document.
A7: Strategy | B7: Sequential batches: sell 1,000 before starting 3,000; sell 3,000 before starting 5,000.
A8: Cash policy | B8: Reserve next-cycle working capital and obligations first; compare maximum withdrawal with 1-, 2-, and 3-month reserve policies once operating expenses are known.

Sheet Historical Baseline
A1: category | B1: metric | C1: value | D1: unit | E1: status | F1: notes
A2: Production | B2: Birds placed | C2: 50 | D2: birds | E2: Actual | F2: 50 day-old chicks purchased
A3: Production | B3: Birds died | C3: 2 | D3: birds | E3: Actual | F3: Reported by user
A4: Production | B4: Birds sold | C4: 48 | D4: birds | E4: Actual | F4: Reported by user
A5: Revenue | B5: Total sales revenue | C5: 830000 | D5: NGN | E5: Approximate actual | F5: User clarified this is total sales revenue, not profit
A6: Cost | B6: Day-old chicks | C6: 102500 | D6: NGN | E6: Actual/documented | F6: 50 chicks at ₦2,050 each
A7: Cost | B7: Commercial starter feed | C7: 100400 | D7: NGN | E7: Actual/documented | F7: 4 bags × 25kg; amount from original research
A8: Cost | B8: Commercial finisher feed | C8: 86000 | D8: NGN | E8: Actual/documented | F8: 4 bags × 25kg; amount from original research
A9: Cost | B9: Medication and supplements | C9: 17000 | D9: NGN | E9: Approximate actual | F9: Approximate amount reported by user
A10: Cost | B10: Other operating expenses | D10: NGN | E10: Unknown | F10: Must be collected; excluded from preliminary surplus
A11: Feed alternative | B11: In-house starter feed estimate | C11: 45000 | D11: NGN per 50-bird batch | E11: Estimate only | F11: Not implemented in actual cycle; ingredient-price estimate
A12: Feed alternative | B12: In-house finisher feed estimate | C12: 45000 | D12: NGN per 50-bird batch | E12: Estimate only | F12: Not implemented in actual cycle; ingredient-price estimate
A13: Feed alternative | B13: In-house feed total estimate | C13: 90000 | D13: NGN per 50-bird batch | E13: Estimate only | F13: Excludes transport, milling, fuel/power, labour, wastage, quality control and equipment costs
A14: Capital plan | B14: Truck, feed mill, solar, incubator | D14: NGN | E14: Not priced | F14: Planned investments; not treated as already owned or free

Sheet Model Inputs
A1: input | B1: value | C1: unit | D1: status | E1: definition
A2: Survival rate | B2: 0.96 | C2: ratio | D2: Baseline-derived assumption | E2: Can be changed for scenarios; historical batch survival was 96%
A3: Average selling price per bird sold | B3: 17291.667 | C3: NGN/bird | D3: Baseline-derived approximate | E3: ₦830,000 divided by 48 birds sold
A4: Day-old chick cost per bird placed | B4: 2050 | C4: NGN/bird | D4: Baseline-derived actual | E4: Historical purchase cost per chick
A5: Commercial starter + finisher feed per bird placed | B5: 3728 | C5: NGN/bird | D5: Baseline-derived actual | E5: Historical feed cost per bird placed; validate feeding quantities before scale-up
A6: Medication/supplements per bird placed | B6: 340 | C6: NGN/bird | D6: Baseline-derived approximate | E6: Does not include any additional unrecorded veterinary costs
A7: In-house feed estimate per bird placed | B7: 1800 | C7: NGN/bird | D7: Estimate only | E7: Excludes several operating and capital costs; not a proven saving
A8: Other operating costs per bird placed | C8: NGN/bird | D8: Required input missing | E8: Labour, litter, water, fuel, transport, cleaning, extra vaccines, etc.
A9: Capital expenditure before next cycle | C9: NGN | D9: Required input missing | E9: Incubator, truck, mill, solar and infrastructure quotes
A10: Egg cost per fertilized egg | C10: NGN/egg | D10: Required input missing | E10: Needed for hatchery model
A11: Fertility rate | C11: ratio | D11: Required input missing | E11: Measure or use clearly labelled scenario assumptions
A12: Hatchability of fertile eggs | C12: ratio | D12: Required input missing | E12: Measure or use clearly labelled scenario assumptions
A13: Usable chick rate after hatch | C13: ratio | D13: Required input missing | E13: Measure or use clearly labelled scenario assumptions
A14: Fuel and transport per cycle | C14: NGN/cycle | D14: Required input missing | E14: Truck purchase does not eliminate fuel and maintenance costs
A15: Scenario control
A16: Target bird counts | B16: 1000;3000;5000 | C16: birds | D16: Illustration | E16: Edit in Scale Model if required
A17: Sale price shock | B17: 0.9 | C17: multiplier | D17: Sensitivity input | E17: 0.9 means 10% lower selling price
A18: Known cost shock | B18: 1.1 | C18: multiplier | D18: Sensitivity input | E18: 1.1 means 10% higher known costs
A19: Downside survival | B19: 0.92 | C19: ratio | D19: Sensitivity input | E19: Scenario only, not historical result

Sheet Scale Model
A1: Target birds placed | B1: Assumed survival rate | C1: Expected birds sold | D1: Avg sale price / bird sold | E1: Illustrative revenue | F1: Chick cost | G1: Commercial feed cost | H1: Medication/supplements | I1: Known costs: commercial feed | J1: Preliminary surplus before missing costs | K1: Estimated in-house feed cost | L1: Known costs: in-house feed | M1: Preliminary surplus: in-house estimate | N1: Classification
A2: 1000 | B2: ='Model Inputs'!B2 | C2: =A2*B2 | D2: ='Model Inputs'!B3 | E2: =C2*D2 | F2: =A2*'Model Inputs'!B4 | G2: =A2*'Model Inputs'!B5 | H2: =A2*'Model Inputs'!B6 | I2: =F2+G2+H2 | J2: =E2-I2 | K2: =A2*'Model Inputs'!B7 | L2: =F2+H2+K2 | M2: =E2-L2 | N2: Illustrative only; excludes unknown costs/capex
A3: 3000 | B3: ='Model Inputs'!B2 | C3: =A3*B3 | D3: ='Model Inputs'!B3 | E3: =C3*D3 | F3: =A3*'Model Inputs'!B4 | G3: =A3*'Model Inputs'!B5 | H3: =A3*'Model Inputs'!B6 | I3: =F3+G3+H3 | J3: =E3-I3 | K3: =A3*'Model Inputs'!B7 | L3: =F3+H3+K3 | M3: =E3-L3 | N3: Illustrative only; excludes unknown costs/capex
A4: 5000 | B4: ='Model Inputs'!B2 | C4: =A4*B4 | D4: ='Model Inputs'!B3 | E4: =C4*D4 | F4: =A4*'Model Inputs'!B4 | G4: =A4*'Model Inputs'!B5 | H4: =A4*'Model Inputs'!B6 | I4: =F4+G4+H4 | J4: =E4-I4 | K4: =A4*'Model Inputs'!B7 | L4: =F4+H4+K4 | M4: =E4-L4 | N4: Illustrative only; excludes unknown costs/capex

Sheet Sensitivity
A1: Scenario | B1: Birds placed | C1: Survival rate | D1: Price multiplier | E1: Known cost multiplier | F1: Illustrative revenue | G1: Known costs only | H1: Preliminary surplus before missing costs/capex | I1: Warning
A2: Baseline-equivalent illustration | B2: 5000 | C2: ='Model Inputs'!B2 | D2: 1 | E2: 1 | F2: =B2*C2*'Model Inputs'!B3 | G2: =B2*('Model Inputs'!B4+'Model Inputs'!B5+'Model Inputs'!B6) | H2: =F2-G2 | I2: Illustrative only
A3: Selling price down 10% | B3: 5000 | C3: ='Model Inputs'!B2 | D3: 0.9 | E3: 1 | F3: =B3*C3*'Model Inputs'!B3*D3 | G3: =B3*('Model Inputs'!B4+'Model Inputs'!B5+'Model Inputs'!B6)*E3 | H3: =F3-G3 | I3: Illustrative only
A4: Known unit costs up 10% | B4: 5000 | C4: ='Model Inputs'!B2 | D4: 1 | E4: 1.1 | F4: =B4*C4*'Model Inputs'!B3*D4 | G4: =B4*('Model Inputs'!B4+'Model Inputs'!B5+'Model Inputs'!B6)*E4 | H4: =F4-G4 | I4: Illustrative only
A5: Survival falls to 92% | B5: 5000 | C5: ='Model Inputs'!B19 | D5: 1 | E5: 1 | F5: =B5*C5*'Model Inputs'!B3*D5 | G5: =B5*('Model Inputs'!B4+'Model Inputs'!B5+'Model Inputs'!B6)*E5 | H5: =F5-G5 | I5: Illustrative only
A6: Price down 10% and costs up 10% | B6: 5000 | C6: ='Model Inputs'!B2 | D6: 0.9 | E6: 1.1 | F6: =B6*C6*'Model Inputs'!B3*D6 | G6: =B6*('Model Inputs'!B4+'Model Inputs'!B5+'Model Inputs'!B6)*E6 | H6: =F6-G6 | I6: Illustrative only
A7: Price down 10%, survival 92%, costs up 10% | B7: 5000 | C7: ='Model Inputs'!B19 | D7: 0.9 | E7: 1.1 | F7: =B7*C7*'Model Inputs'!B3*D7 | G7: =B7*('Model Inputs'!B4+'Model Inputs'!B5+'Model Inputs'!B6)*E7 | H7: =F7-G7 | I7: Illustrative only

Sheet Cash Allocation
A1: Cash allocation framework | B1: Amount (NGN) | C1: Notes
A2: Cash available after current cycle | C2: Input after reconciling all receipts and costs
A3: Next-cycle working capital | C3: Must be estimated from validated 1k/3k/5k cost plan
A4: Outstanding obligations | C4: Input
A5: Emergency reserve target | C5: Use 1/2/3 months of operating expenses
A6: Maximum safe withdrawal | B6: =MAX(0,B2-B3-B4-B5) | C6: Only after next-cycle working capital and reserve
A7: Conservative withdrawal | B7: =MAX(0,B2-B3-B4-B5) | C7: Set a larger reserve amount in row 5 to test conservative policy
A8: Important | C8: Do not use until all unknown costs and capital obligations are entered.

Sheet Hatchery Inputs
A1: Input | B1: Value | C1: Unit | D1: Status / notes
A2: Fertilized egg price | C2: NGN/egg | D2: Required input
A3: Delivery per batch | C3: NGN/batch | D3: Required input
A4: Fertility rate | C4: ratio | D4: Measured or explicitly scenario-based
A5: Hatchability of fertile eggs | C5: ratio | D5: Measured or explicitly scenario-based
A6: Usable chick rate | C6: ratio | D6: Measured or explicitly scenario-based
A7: Incubator purchase and installation | C7: NGN | D7: Capital expenditure
A8: Power / solar allocation per cycle | C8: NGN/cycle | D8: Include running and maintenance costs
A9: Labour / sanitation per cycle | C9: NGN/cycle | D9: Required input
A10: Vaccination / early chick care per cycle | C10: NGN/cycle | D10: Required input
A11: Incubator maintenance per cycle | C11: NGN/cycle | D11: Required input
A12: Purchased day-old chick price | C12: NGN/chick | D12: Comparator; baseline was ₦2,050/chick
A13: Eggs loaded | C13: eggs | D13: Required input
A14: Expected usable chicks | B14: =IF(OR(B4="",B5="",B6="",B13=""),"",B13*B4*B5*B6) | C14: chicks | D14: Formula; only works once rates are populated
A15: Fully loaded hatchery cost | C15: NGN/cycle | D15: Sum egg, delivery, labour, power, care, maintenance and allocated capex
A16: Cost per usable chick | B16: =IFERROR(B15/B14,"") | C16: NGN/chick | D16: Compare with day-old chick purchase price

Sheet Power BI Data
A1: stage | B1: metric | C1: value_NGN | D1: data_classification
A2: 1,000 birds | B2: Illustrative Revenue | C2: 16600000 | D2: Illustrative baseline-equivalent scenario
A3: 1,000 birds | B3: Commercial Feed Cost | C3: 3728000 | D3: Illustrative baseline-equivalent scenario
A4: 1,000 birds | B4: Estimated In-house Feed Cost | C4: 1800000 | D4: Illustrative baseline-equivalent scenario
A5: 1,000 birds | B5: Known Costs - Commercial Feed | C5: 6118000 | D5: Illustrative baseline-equivalent scenario
A6: 1,000 birds | B6: Preliminary Surplus - Commercial Feed | C6: 10482000 | D6: Illustrative baseline-equivalent scenario
A7: 1,000 birds | B7: Preliminary Surplus - In-house Feed Estimate | C7: 12410000 | D7: Illustrative baseline-equivalent scenario
A8: 3,000 birds | B8: Illustrative Revenue | C8: 49800000 | D8: Illustrative baseline-equivalent scenario
A9: 3,000 birds | B9: Commercial Feed Cost | C9: 11184000 | D9: Illustrative baseline-equivalent scenario
A10: 3,000 birds | B10: Estimated In-house Feed Cost | C10: 5400000 | D10: Illustrative baseline-equivalent scenario
A11: 3,000 birds | B11: Known Costs - Commercial Feed | C11: 18354000 | D11: Illustrative baseline-equivalent scenario
A12: 3,000 birds | B12: Preliminary Surplus - Commercial Feed | C12: 31446000 | D12: Illustrative baseline-equivalent scenario
A13: 3,000 birds | B13: Preliminary Surplus - In-house Feed Estimate | C13: 37230000 | D13: Illustrative baseline-equivalent scenario
... A19: 5,000 birds | B19: Preliminary Surplus - In-house Feed Estimate | C19: 62050000 | D19: Illustrative baseline-equivalent scenario
